pygame_button/__init__.py
pygame_button/button.py
pygame_button-0.0.3.dist-info/METADATA
pygame_button-0.0.3.dist-info/WHEEL
pygame_button-0.0.3.dist-info/top_level.txt
pygame_button-0.0.3.dist-info/RECORD
