Metadata-Version: 2.1
Name: pygame-button
Version: 0.0.3
Summary: A very simple button class for pygame.
Home-page: https://github.com/Layerex/pygame_button
Author: Layerex
Author-email: layerex@dismail.de
Classifier: Development Status :: 7 - Inactive
Classifier: Topic :: Software Development :: Libraries :: Python Modules
Classifier: Topic :: Software Development :: Libraries :: pygame
Classifier: Programming Language :: Python :: 2
Classifier: Programming Language :: Python :: 3
